{
  "required": true,
  "minVersion": "0.8",
  "package": "io.github.fabriccommunity.events.mixin",
  "compatibilityLevel": "JAVA_8",
  "mixins": [
    "advancement.MixinInventoryChangedCriterion",
    "advancement.MixinItemDurabilityChangedCriterion",
    "advancement.MixinOnKilledCriterion",
    "advancement.MixinPlayerHurtEntityCriterion",
    "biomegen.MixinMultiNoiseBiomeSource",
    "biomegen.MixinTheEndBiomeSource",
    "biomegen.MixinVanillaLayeredBiomeSource",
    "item.MixinBlockItem",
    "item.MixinItem",
    "player.MixinHungerManager",
    "player.MixinPlayerEntity",
    "player.MixinPlayerManager",
    "spawn.MixinEntityType",
    "spawn.MixinMobSpawnerLogic",
    "spawn.MixinSpawnHelper",
    "spawn.MixinSummonCommand"
  ],
  "client": [
    "client.MixinBackgroundRenderer",
    "client.MixinMinecraftClient",
    "client.MixinWorldRenderer"
  ],
  "injectors": {
    "defaultRequire": 1
  }
}
